youtube_dl_tiny_grpc/__init__.py
youtube_dl_tiny_grpc/__main__.py
youtube_dl_tiny_grpc/cache.py
youtube_dl_tiny_grpc/metrics.py
youtube_dl_tiny_grpc/options.py
youtube_dl_tiny_grpc/util.py
youtube_dl_tiny_grpc/version.py
youtube_dl_tiny_grpc/youtube_dl_service.py
youtube_dl_tiny_grpc/youtube_dl_tiny_grpc.py
youtube_dl_tiny_grpc/protobuf/__init__.py
youtube_dl_tiny_grpc/protobuf/youtube_dl_tiny_grpc_pb2.py
youtube_dl_tiny_grpc/protobuf/youtube_dl_tiny_grpc_pb2_grpc.py
youtube_dl_tiny_grpc-0.3.2.dist-info/METADATA
youtube_dl_tiny_grpc-0.3.2.dist-info/WHEEL
youtube_dl_tiny_grpc-0.3.2.dist-info/entry_points.txt
youtube_dl_tiny_grpc-0.3.2.dist-info/top_level.txt
youtube_dl_tiny_grpc-0.3.2.dist-info/RECORD
