Metadata-Version: 2.1
Name: youtube-dl-tiny-grpc
Version: 0.3.2
Summary: A tiny slice of youtube-dl exposed over gRPC
Home-page: https://github.com/someone-stole-my-name/youtube-dl-tiny-grpc
Author: Christian Segundo
Author-email: chn2guevara@gmail.com
License: UNKNOWN
Project-URL: Bug Tracker, https://github.com/someone-stole-my-name/youtube-dl-tiny-grpc/issues
Platform: UNKNOWN
Classifier: Programming Language :: Python :: 3
Classifier: License :: OSI Approved :: MIT License
Classifier: Operating System :: OS Independent
Requires-Python: >=3.8
Requires-Dist: aioredis (>=2.0.1)
Requires-Dist: asyncio (>=3.4.3)
Requires-Dist: grpcio-reflection (>=1.44.0)
Requires-Dist: grpcio-tools (>=1.44.0)
Requires-Dist: hiredis (>=2.0.0)
Requires-Dist: prometheus-client (==0.14.1)
Requires-Dist: setproctitle (>=1.2.2)
Requires-Dist: youtube-dl (>=2021.12.17)
